[
  {
    "RB1":"Josh Jacobs",
    "DK Sal":"10600",
    "FD Sal":"12400",
    "Ru Attempts":"18.9",
    "YPC":"4.4",
    "Rush Yards":"82.8",
    "Rush TD":"0.8",
    "Targets":"2.9",
    "Tgt Share":"9.9%",
    "Rec":"2.0",
    "Rec Yards":"17.2",
    "Rec TD":"0.1",
    "DK Proj":"19.0",
    "DK Val":"1.8",
    "FD Proj":"18.0",
    "FD Val":"1.5"
  },
  {
    "RB1":"Austin Ekeler",
    "DK Sal":"6800",
    "FD Sal":"7800",
    "Ru Attempts":"10.6",
    "YPC":"4.4",
    "Rush Yards":"46.8",
    "Rush TD":"0.4",
    "Targets":"3.7",
    "Tgt Share":"11.7%",
    "Rec":"3.0",
    "Rec Yards":"23.5",
    "Rec TD":"0.1",
    "DK Proj":"14.2",
    "DK Val":"2.1",
    "FD Proj":"12.7",
    "FD Val":"1.6"
  },
  {
    "RB1":"Jacory Croskey-Merritt",
    "DK Sal":"7000",
    "FD Sal":"8600",
    "Ru Attempts":"9.9",
    "YPC":"4.5",
    "Rush Yards":"44.8",
    "Rush TD":"0.4",
    "Targets":"1.8",
    "Tgt Share":"5.8%",
    "Rec":"1.2",
    "Rec Yards":"10.3",
    "Rec TD":"0.0",
    "DK Proj":"10.1",
    "DK Val":"1.4",
    "FD Proj":"9.5",
    "FD Val":"1.1"
  },
  {
    "RB1":"Emanuel Wilson",
    "DK Sal":"2000",
    "FD Sal":"2400",
    "Ru Attempts":"4.6",
    "YPC":"4.8",
    "Rush Yards":"22.5",
    "Rush TD":"0.1",
    "Targets":"1.0",
    "Tgt Share":"3.4%",
    "Rec":"0.7",
    "Rec Yards":"4.6",
    "Rec TD":"0.1",
    "DK Proj":"5.1",
    "DK Val":"2.5",
    "FD Proj":"4.7",
    "FD Val":"2.0"
  },
  {
    "RB1":"Chris Brooks",
    "DK Sal":"400",
    "FD Sal":"1200",
    "Ru Attempts":"1.2",
    "YPC":"4.8",
    "Rush Yards":"5.8",
    "Rush TD":"0.1",
    "Targets":"0.8",
    "Tgt Share":"2.6%",
    "Rec":"0.6",
    "Rec Yards":"4.4",
    "Rec TD":"0.0",
    "DK Proj":"2.6",
    "DK Val":"6.6",
    "FD Proj":"2.3",
    "FD Val":"1.9"
  },
  {
    "RB1":"Chris Rodriguez Jr.",
    "DK Sal":"1400",
    "FD Sal":"2000",
    "Ru Attempts":"0.4",
    "YPC":"4.3",
    "Rush Yards":"1.7",
    "Rush TD":"0.1",
    "Targets":"0.0",
    "Tgt Share":"0.1%",
    "Rec":"0.0",
    "Rec Yards":"0.1",
    "Rec TD":"0",
    "DK Proj":"1.1",
    "DK Val":"0.8",
    "FD Proj":"1.1",
    "FD Val":"0.5"
  }
]