[
  {
    "POS":"TE",
    "Player":"Mark Andrews",
    "DK Sal":"7000",
    "FD Sal":"8600",
    "Team":"BAL",
    "OPP":"BUF",
    "Home":"BUF",
    "Time":"20:20:00",
    "O\/U":"50.5",
    "Imp Total":"25.5",
    "Line":"1.5",
    "Rec Yds":"39.6",
    "Rec":"3.2",
    "Targets":"4.1",
    "TD":"0.6",
    "Tgt Shr":"15%",
    "Routes%":"51.6%",
    "Block%":"11.3%",
    "MsAir":"17.1%",
    "adot":"10",
    "DK Pts":"12.4",
    "Rank":"18",
    "Yards":"48.2",
    "TD_1":"0.3",
    "Vegas":"1.2%",
    "DVP":"100.1%",
    "Proj":"11.7",
    "Value":"1.7",
    "Proj_1":"9.6",
    "Value_1":"1.1"
  },
  {
    "POS":"TE",
    "Player":"Dalton Kincaid",
    "DK Sal":"5600",
    "FD Sal":"5400",
    "Team":"BUF",
    "OPP":"BAL",
    "Home":"BUF",
    "Time":"20:20:00",
    "O\/U":"50.5",
    "Imp Total":"26.5",
    "Line":"-1.5",
    "Rec Yds":"34.5",
    "Rec":"3.4",
    "Targets":"5.8",
    "TD":"0.2",
    "Tgt Shr":"20.2%",
    "Routes%":"62%",
    "Block%":"9%",
    "MsAir":"19.4%",
    "adot":"7.7",
    "DK Pts":"13.1",
    "Rank":"20",
    "Yards":"56.6",
    "TD_1":"0.3",
    "Vegas":"1.2%",
    "DVP":"1.1%",
    "Proj":"8.9",
    "Value":"1.6",
    "Proj_1":"7.1",
    "Value_1":"1.3"
  },
  {
    "POS":"TE",
    "Player":"Dawson Knox",
    "DK Sal":"3600",
    "FD Sal":"3000",
    "Team":"BUF",
    "OPP":"BAL",
    "Home":"BUF",
    "Time":"20:20:00",
    "O\/U":"50.5",
    "Imp Total":"26.5",
    "Line":"-1.5",
    "Rec Yds":"22.2",
    "Rec":"1.6",
    "Targets":"2.4",
    "TD":"0.1",
    "Tgt Shr":"7.1%",
    "Routes%":"47.2%",
    "Block%":"9.6%",
    "MsAir":"8.1%",
    "adot":"9.2",
    "DK Pts":"13.1",
    "Rank":"20",
    "Yards":"56.6",
    "TD_1":"0.3",
    "Vegas":"1.2%",
    "DVP":"1.1%",
    "Proj":"3.3",
    "Value":"0.9",
    "Proj_1":"2.8",
    "Value_1":"0.9"
  },
  {
    "POS":"TE",
    "Player":"Charlie Kolar",
    "DK Sal":"1600",
    "FD Sal":"1200",
    "Team":"BAL",
    "OPP":"BUF",
    "Home":"BUF",
    "Time":"20:20:00",
    "O\/U":"50.5",
    "Imp Total":"25.5",
    "Line":"1.5",
    "Rec Yds":"18.7",
    "Rec":"1.3",
    "Targets":"1.6",
    "TD":"0.1",
    "Tgt Shr":"3.3%",
    "Routes%":"16.3%",
    "Block%":"9.6%",
    "MsAir":"2.3%",
    "adot":"6.4",
    "DK Pts":"12.4",
    "Rank":"18",
    "Yards":"48.2",
    "TD_1":"0.3",
    "Vegas":"1.2%",
    "DVP":"100.1%",
    "Proj":"3.8",
    "Value":"2.4",
    "Proj_1":"3.2",
    "Value_1":"2.6"
  },
  {
    "POS":"TE",
    "Player":"Zaire Mitchell-Paden",
    "DK Sal":"200",
    "FD Sal":"1000",
    "Team":"BAL",
    "OPP":"BUF",
    "Home":"BUF",
    "Time":"20:20:00",
    "O\/U":"50.5",
    "Imp Total":"25.5",
    "Line":"1.5",
    "Rec Yds":"",
    "Rec":"",
    "Targets":"",
    "TD":"",
    "Tgt Shr":"",
    "Routes%":"",
    "Block%":"",
    "MsAir":"",
    "adot":"",
    "DK Pts":"12.4",
    "Rank":"18",
    "Yards":"48.2",
    "TD_1":"0.3",
    "Vegas":"1.2%",
    "DVP":"100.1%",
    "Proj":"0.4",
    "Value":"1.8",
    "Proj_1":"0.4",
    "Value_1":"0.4"
  },
  {
    "POS":"TE",
    "Player":"Jackson Hawes",
    "DK Sal":"200",
    "FD Sal":"1000",
    "Team":"BUF",
    "OPP":"BAL",
    "Home":"BUF",
    "Time":"20:20:00",
    "O\/U":"50.5",
    "Imp Total":"26.5",
    "Line":"-1.5",
    "Rec Yds":"",
    "Rec":"",
    "Targets":"",
    "TD":"",
    "Tgt Shr":"",
    "Routes%":"",
    "Block%":"",
    "MsAir":"",
    "adot":"",
    "DK Pts":"13.1",
    "Rank":"20",
    "Yards":"56.6",
    "TD_1":"0.3",
    "Vegas":"1.2%",
    "DVP":"1.1%",
    "Proj":"0.4",
    "Value":"2.0",
    "Proj_1":"0.3",
    "Value_1":"0.3"
  }
]